{
    "configurations": [
        {
            "name": "Win32",
            "includePath": [
                "${workspaceFolder}/**",
                "E:/github/tensorflow/tf2.2-libs/",
                "E:/github/tensorflow/tf2.2-libs/tensorflow",
                "E:/github/tensorflow/tf2.2-libs/third_party/",
                "E:/github/tensorflow/tf2.2-libs/protobuf-3.9.0/include",
                "E:/github/tensorflow/tf2.2-libs/absl/include",
                "E:/github/tensorflow/tf2.2-libs/eigen3",
                "E:/github/tensorflow/tensorflow/"
            ],
            "defines": [
                "_DEBUG",
                "UNICODE",
                "_UNICODE"
            ],
            "windowsSdkVersion": "8.1",
            "compilerPath": "D:\\install\\mingw64\\mingw64\\bin\\gdb.exe",
            "cStandard": "c11",
            "cppStandard": "c++17",
            "intelliSenseMode": "gcc-x64"
        }
    ],
    "version": 4
}